simplestat/__init__.py
simplestat/content.py
simplestat-0.8.dist-info/LICENSE
simplestat-0.8.dist-info/METADATA
simplestat-0.8.dist-info/WHEEL
simplestat-0.8.dist-info/top_level.txt
simplestat-0.8.dist-info/RECORD
