Metadata-Version: 2.1
Name: simplestat
Version: 0.8
Summary: Very minimal statistics module. Useful when you dont have the disk space for numpy
Home-page: https://github.com/psorus/simplestat/
Author: Simon Klüttermann
Author-email: Simon.Kluettermann@gmx.de
License: UNKNOWN
Download-URL: https://github.com/psorus/simplestat/archive/0.8.tar.gz
Platform: UNKNOWN
Classifier: Programming Language :: Python :: 3
Classifier: License :: OSI Approved :: MIT License
Classifier: Operating System :: OS Independent
Requires-Python: >=2.7
